firebase/__init__.py
firebase/async_compatible.py
firebase/decorators.py
firebase/firebase.py
firebase/firebase_token_generator.py
firebase/jsonutil.py
firebase/lazy.py
firebase-4.0.1.dist-info/LICENCE
firebase-4.0.1.dist-info/METADATA
firebase-4.0.1.dist-info/WHEEL
firebase-4.0.1.dist-info/top_level.txt
firebase-4.0.1.dist-info/RECORD
