Metadata-Version: 2.1
Name: firebase
Version: 4.0.1
Summary: Python interface to the Google's Firebase REST APIs
Home-page: https://bitbucket.org/joetilsed/firebase/
Author: Joe Tilsed
Author-email: Joe@Tilsed.com
Keywords: firebase python
Classifier: Programming Language :: Python :: 3.10
Classifier: Natural Language :: English
Classifier: Intended Audience :: Developers
Classifier: License :: OSI Approved :: MIT License
Classifier: Operating System :: OS Independent
License-File: LICENCE
